isoxml/__init__.py
isoxml/converter/__init__.py
isoxml/converter/np_grid.py
isoxml/converter/shapely_geom.py
isoxml/models/__init__.py
isoxml/models/ddi_entities.py
isoxml/models/base/__init__.py
isoxml/models/base/v3/__init__.py
isoxml/models/base/v3/allocation_stamp.py
isoxml/models/base/v3/coded_comment.py
isoxml/models/base/v3/coded_comment_group.py
isoxml/models/base/v3/coded_comment_list_value.py
isoxml/models/base/v3/colour_legend.py
isoxml/models/base/v3/colour_range.py
isoxml/models/base/v3/comment_allocation.py
isoxml/models/base/v3/connection.py
isoxml/models/base/v3/crop_type.py
isoxml/models/base/v3/crop_variety.py
isoxml/models/base/v3/cultural_practice.py
isoxml/models/base/v3/customer.py
isoxml/models/base/v3/data_log_trigger.py
isoxml/models/base/v3/data_log_value.py
isoxml/models/base/v3/device.py
isoxml/models/base/v3/device_allocation.py
isoxml/models/base/v3/device_element.py
isoxml/models/base/v3/device_object_reference.py
isoxml/models/base/v3/device_process_data.py
isoxml/models/base/v3/device_property.py
isoxml/models/base/v3/device_value_presentation.py
isoxml/models/base/v3/external_file_contents.py
isoxml/models/base/v3/external_file_reference.py
isoxml/models/base/v3/farm.py
isoxml/models/base/v3/grid.py
isoxml/models/base/v3/iso11783_task_data.py
isoxml/models/base/v3/line_string.py
isoxml/models/base/v3/oper_tech_practice.py
isoxml/models/base/v3/operation_technique.py
isoxml/models/base/v3/operation_technique_reference.py
isoxml/models/base/v3/partfield.py
isoxml/models/base/v3/point.py
isoxml/models/base/v3/polygon.py
isoxml/models/base/v3/position.py
isoxml/models/base/v3/process_data_variable.py
isoxml/models/base/v3/product.py
isoxml/models/base/v3/product_allocation.py
isoxml/models/base/v3/product_group.py
isoxml/models/base/v3/task.py
isoxml/models/base/v3/time.py
isoxml/models/base/v3/time_log.py
isoxml/models/base/v3/treatment_zone.py
isoxml/models/base/v3/value_presentation.py
isoxml/models/base/v3/worker.py
isoxml-0.0.4.dist-info/LICENSE
isoxml-0.0.4.dist-info/METADATA
isoxml-0.0.4.dist-info/WHEEL
isoxml-0.0.4.dist-info/top_level.txt
isoxml-0.0.4.dist-info/RECORD
