Metadata-Version: 2.1
Name: isoxml
Version: 0.0.4
Summary: Python ISOXML read/write
Author: Josephinum-Research
License: Apache License 2.0
Project-URL: Homepage, https://github.com/Josephinum-Research/isoxml-py
Project-URL: Issues, https://github.com/Josephinum-Research/isoxml-py/issues
Keywords: isoxml,isobus,iso,11783-10,xml,precision farming
Classifier: Programming Language :: Python :: 3
Classifier: Operating System :: OS Independent
Requires-Python: >=3.10
License-File: LICENSE
Requires-Dist: xsdata >=24.7
Requires-Dist: numpy >=1.26
Requires-Dist: shapely >=2.0
Provides-Extra: dev
Requires-Dist: xsdata[cli] ; extra == 'dev'
Requires-Dist: geopandas ; extra == 'dev'
Requires-Dist: xmlschema ; extra == 'dev'
Requires-Dist: jupyter ; extra == 'dev'
Requires-Dist: folium ; extra == 'dev'
Requires-Dist: matplotlib ; extra == 'dev'
Requires-Dist: mapclassify ; extra == 'dev'
Provides-Extra: test
Requires-Dist: pytest ; extra == 'test'
Requires-Dist: xmlschema ; extra == 'test'
